matter_api_client/__about__.py
matter_api_client/__init__.py
matter_api_client/config.py
matter_api_client/decorators.py
matter_api_client/exceptions.py
matter_api_client/http_client.py
matter_api_client/http_client_async.py
matter_api_client/response.py
matter_api_client-1.2.0.dist-info/METADATA
matter_api_client-1.2.0.dist-info/WHEEL
matter_api_client-1.2.0.dist-info/licenses/LICENSE
matter_api_client-1.2.0.dist-info/RECORD
