Metadata-Version: 2.1
Name: matter-api-client
Version: 1.2.0
Summary: Matter's API Client Library
Project-URL: Documentation, https://github.com/Matter-Tech/matter-api-client#readme
Project-URL: Issues, https://github.com/Matter-Tech/matter-api-client/issues
Project-URL: Source, https://github.com/Matter-Tech/matter-api-client
Author-email: Tomer Sasson <tomer@thisismatter.com>
License-Expression: MIT
License-File: LICENSE
Classifier: Development Status :: 4 - Beta
Classifier: Programming Language :: Python
Classifier: Programming Language :: Python :: 3.10
Classifier: Programming Language :: Python :: 3.11
Classifier: Programming Language :: Python :: Implementation :: CPython
Classifier: Programming Language :: Python :: Implementation :: PyPy
Requires-Python: >=3.10
Requires-Dist: aiohttp>=3.8.4
Requires-Dist: matter-exceptions>=1.1.0
Requires-Dist: orjson>=3.8.10
Requires-Dist: requests>=2.28.2
